{
    "A": [{
            "id": "1199",
            "name": "奥迪",
            "icon": "https://image.guazistatic.com/files/brand/1199.png"
        },
        {
            "id": "1217",
            "name": "阿尔法·罗密欧",
            "icon": "https://image.guazistatic.com/files/brand/1217.png"
        },
        {
            "id": "1218",
            "name": "阿斯顿·马丁",
            "icon": "https://image.guazistatic.com/files/brand/1218.png"
        },
        {
            "id": "103803",
            "name": "AC Schnitzer",
            "icon": "https://image.guazistatic.com/files/brand/103803.png"
        },
        {
            "id": "103841",
            "name": "ARCFOX",
            "icon": "https://image.guazistatic.com/files/brand/103841.png"
        },
        {
            "id": "103764",
            "name": "Alpina",
            "icon": "https://image.guazistatic.com/files/brand/103764.png"
        },
        {
            "id": "103819",
            "name": "安凯客车",
            "icon": "https://image.guazistatic.com/files/brand/103819.png"
        },
        {
            "id": "1219",
            "name": "安驰",
            "icon": "https://image.guazistatic.com/files/brand/1219.png"
        }
    ],
    "B": [{
            "id": "1206",
            "name": "别克",
            "icon": "https://image.guazistatic.com/files/brand/1206.png"
        },
        {
            "id": "1196",
            "name": "本田",
            "icon": "https://image.guazistatic.com/files/brand/1196.png"
        },
        {
            "id": "1198",
            "name": "宝马",
            "icon": "https://image.guazistatic.com/files/brand/1198.png"
        },
        {
            "id": "1197",
            "name": "奔驰",
            "icon": "https://image.guazistatic.com/files/brand/1197.png"
        },
        {
            "id": "1212",
            "name": "比亚迪",
            "icon": "https://image.guazistatic.com/files/brand/1212.png"
        },
        {
            "id": "1226",
            "name": "标致",
            "icon": "https://image.guazistatic.com/files/brand/1226.png"
        },
        {
            "id": "2272",
            "name": "宝骏",
            "icon": "https://image.guazistatic.com/files/brand/2272.png"
        },
        {
            "id": "1225",
            "name": "奔腾",
            "icon": "https://image.guazistatic.com/files/brand/1225.png"
        },
        {
            "id": "103783",
            "name": "北汽绅宝",
            "icon": "https://image.guazistatic.com/files/brand/103783.png"
        },
        {
            "id": "103780",
            "name": "北汽幻速",
            "icon": "https://image.guazistatic.com/files/brand/103780.png"
        },
        {
            "id": "1224",
            "name": "保时捷",
            "icon": "https://image.guazistatic.com/files/brand/1224.png"
        },
        {
            "id": "2270",
            "name": "北京",
            "icon": "https://image.guazistatic.com/files/brand/2270.png"
        },
        {
            "id": "103779",
            "name": "北汽威旺",
            "icon": "https://image.guazistatic.com/files/brand/103779.png"
        },
        {
            "id": "103798",
            "name": "宝沃汽车",
            "icon": "https://image.guazistatic.com/files/brand/103798.png"
        },
        {
            "id": "1223",
            "name": "北汽",
            "icon": "https://image.guazistatic.com/files/brand/1223.png"
        },
        {
            "id": "103807",
            "name": "比速汽车",
            "icon": "https://image.guazistatic.com/files/brand/103807.png"
        },
        {
            "id": "103826",
            "name": "北汽新能源",
            "icon": "https://image.guazistatic.com/files/brand/103826.png"
        },
        {
            "id": "1222",
            "name": "宾利",
            "icon": "https://image.guazistatic.com/files/brand/1222.png"
        },
        {
            "id": "102721",
            "name": "巴博斯",
            "icon": "https://image.guazistatic.com/files/brand/102721.png"
        },
        {
            "id": "103852",
            "name": "北汽道达",
            "icon": "https://image.guazistatic.com/files/brand/103852.png"
        },
        {
            "id": "103774",
            "name": "保斐利",
            "icon": "https://image.guazistatic.com/files/brand/103774.png"
        },
        {
            "id": "2259",
            "name": "布加迪",
            "icon": "https://image.guazistatic.com/files/brand/2259.png"
        },
        {
            "id": "1221",
            "name": "宝龙",
            "icon": "https://image.guazistatic.com/files/brand/1221.png"
        }
    ],
    "C": [{
            "id": "1227",
            "name": "长安",
            "icon": "https://image.guazistatic.com/files/brand/1227.png"
        },
        {
            "id": "103772",
            "name": "传祺",
            "icon": "https://image.guazistatic.com/files/brand/103772.png"
        },
        {
            "id": "1228",
            "name": "长城",
            "icon": "https://image.guazistatic.com/files/brand/1228.png"
        },
        {
            "id": "103787",
            "name": "长安商用",
            "icon": "https://image.guazistatic.com/files/brand/103787.png"
        },
        {
            "id": "2266",
            "name": "川汽野马",
            "icon": "https://image.guazistatic.com/files/brand/2266.png"
        },
        {
            "id": "1229",
            "name": "昌河",
            "icon": "https://image.guazistatic.com/files/brand/1229.png"
        },
        {
            "id": "103840",
            "name": "长安欧尚",
            "icon": "https://image.guazistatic.com/files/brand/103840.png"
        },
        {
            "id": "103799",
            "name": "成功汽车",
            "icon": "https://image.guazistatic.com/files/brand/103799.png"
        },
        {
            "id": "103812",
            "name": "长安跨越",
            "icon": "https://image.guazistatic.com/files/brand/103812.png"
        }
    ],
    "D": [{
            "id": "1207",
            "name": "大众",
            "icon": "https://image.guazistatic.com/files/brand/1207.png"
        },
        {
            "id": "1239",
            "name": "东风风行",
            "icon": "https://image.guazistatic.com/files/brand/1239.png"
        },
        {
            "id": "1234",
            "name": "东南",
            "icon": "https://image.guazistatic.com/files/brand/1234.png"
        },
        {
            "id": "2262",
            "name": "东风风神",
            "icon": "https://image.guazistatic.com/files/brand/2262.png"
        },
        {
            "id": "102712",
            "name": "东风小康",
            "icon": "https://image.guazistatic.com/files/brand/102712.png"
        },
        {
            "id": "1235",
            "name": "道奇",
            "icon": "https://image.guazistatic.com/files/brand/1235.png"
        },
        {
            "id": "103765",
            "name": "DS",
            "icon": "https://image.guazistatic.com/files/brand/103765.png"
        },
        {
            "id": "1230",
            "name": "东风",
            "icon": "https://image.guazistatic.com/files/brand/1230.png"
        },
        {
            "id": "103769",
            "name": "东风风度",
            "icon": "https://image.guazistatic.com/files/brand/103769.png"
        },
        {
            "id": "103847",
            "name": "电咖汽车",
            "icon": "https://image.guazistatic.com/files/brand/103847.png"
        },
        {
            "id": "1231",
            "name": "大迪",
            "icon": "https://image.guazistatic.com/files/brand/1231.png"
        },
        {
            "id": "1232",
            "name": "大宇",
            "icon": "https://image.guazistatic.com/files/brand/1232.png"
        },
        {
            "id": "1233",
            "name": "大发",
            "icon": "https://image.guazistatic.com/files/brand/1233.png"
        }
    ],
    "F": [{
            "id": "1205",
            "name": "福特",
            "icon": "https://image.guazistatic.com/files/brand/1205.png"
        },
        {
            "id": "1195",
            "name": "丰田",
            "icon": "https://image.guazistatic.com/files/brand/1195.png"
        },
        {
            "id": "1240",
            "name": "菲亚特",
            "icon": "https://image.guazistatic.com/files/brand/1240.png"
        },
        {
            "id": "1215",
            "name": "福田",
            "icon": "https://image.guazistatic.com/files/brand/1215.png"
        },
        {
            "id": "1236",
            "name": "福迪",
            "icon": "https://image.guazistatic.com/files/brand/1236.png"
        },
        {
            "id": "102709",
            "name": "福汽启腾",
            "icon": "https://image.guazistatic.com/files/brand/102709.png"
        },
        {
            "id": "1237",
            "name": "法拉利",
            "icon": "https://image.guazistatic.com/files/brand/1237.png"
        },
        {
            "id": "1238",
            "name": "富奇",
            "icon": "https://image.guazistatic.com/files/brand/1238.png"
        }
    ],
    "G": [{
            "id": "102708",
            "name": "观致",
            "icon": "https://image.guazistatic.com/files/brand/102708.png"
        },
        {
            "id": "1260",
            "name": "广汽吉奥",
            "icon": "https://image.guazistatic.com/files/brand/1260.png"
        },
        {
            "id": "1242",
            "name": "GMC",
            "icon": "https://image.guazistatic.com/files/brand/1242.png"
        },
        {
            "id": "103850",
            "name": "国金汽车",
            "icon": "https://image.guazistatic.com/files/brand/103850.png"
        },
        {
            "id": "1241",
            "name": "光冈",
            "icon": "https://image.guazistatic.com/files/brand/1241.png"
        }
    ],
    "H": [{
            "id": "103778",
            "name": "哈弗",
            "icon": "https://image.guazistatic.com/files/brand/103778.png"
        },
        {
            "id": "1252",
            "name": "海马",
            "icon": "https://image.guazistatic.com/files/brand/1252.png"
        },
        {
            "id": "1256",
            "name": "华泰",
            "icon": "https://image.guazistatic.com/files/brand/1256.png"
        },
        {
            "id": "103797",
            "name": "汉腾",
            "icon": "https://image.guazistatic.com/files/brand/103797.png"
        },
        {
            "id": "1255",
            "name": "红旗",
            "icon": "https://image.guazistatic.com/files/brand/1255.png"
        },
        {
            "id": "1248",
            "name": "哈飞",
            "icon": "https://image.guazistatic.com/files/brand/1248.png"
        },
        {
            "id": "102471",
            "name": "黄海",
            "icon": "https://image.guazistatic.com/files/brand/102471.png"
        },
        {
            "id": "103795",
            "name": "华颂",
            "icon": "https://image.guazistatic.com/files/brand/103795.png"
        },
        {
            "id": "103782",
            "name": "海格",
            "icon": "https://image.guazistatic.com/files/brand/103782.png"
        },
        {
            "id": "103823",
            "name": "华泰新能源",
            "icon": "https://image.guazistatic.com/files/brand/103823.png"
        },
        {
            "id": "1253",
            "name": "悍马",
            "icon": "https://image.guazistatic.com/files/brand/1253.png"
        },
        {
            "id": "1259",
            "name": "汇众",
            "icon": "https://image.guazistatic.com/files/brand/1259.png"
        },
        {
            "id": "1254",
            "name": "华普",
            "icon": "https://image.guazistatic.com/files/brand/1254.png"
        },
        {
            "id": "103842",
            "name": "华晨鑫源",
            "icon": "https://image.guazistatic.com/files/brand/103842.png"
        },
        {
            "id": "102707",
            "name": "恒天",
            "icon": "https://image.guazistatic.com/files/brand/102707.png"
        },
        {
            "id": "103777",
            "name": "华阳",
            "icon": "https://image.guazistatic.com/files/brand/103777.png"
        },
        {
            "id": "1316",
            "name": "华北",
            "icon": "https://image.guazistatic.com/files/brand/1316.png"
        },
        {
            "id": "103808",
            "name": "华凯",
            "icon": "https://image.guazistatic.com/files/brand/103808.png"
        },
        {
            "id": "1247",
            "name": "黑豹",
            "icon": "https://image.guazistatic.com/files/brand/1247.png"
        }
    ],
    "J": [{
            "id": "1200",
            "name": "吉利",
            "icon": "https://image.guazistatic.com/files/brand/1200.png"
        },
        {
            "id": "1264",
            "name": "江淮",
            "icon": "https://image.guazistatic.com/files/brand/1264.png"
        },
        {
            "id": "1216",
            "name": "Jeep",
            "icon": "https://image.guazistatic.com/files/brand/1216.png"
        },
        {
            "id": "1262",
            "name": "捷豹",
            "icon": "https://image.guazistatic.com/files/brand/1262.png"
        },
        {
            "id": "1261",
            "name": "金杯",
            "icon": "https://image.guazistatic.com/files/brand/1261.png"
        },
        {
            "id": "1265",
            "name": "江铃",
            "icon": "https://image.guazistatic.com/files/brand/1265.png"
        },
        {
            "id": "103825",
            "name": "江铃集团新能源",
            "icon": "https://image.guazistatic.com/files/brand/103825.png"
        },
        {
            "id": "103805",
            "name": "金龙",
            "icon": "https://image.guazistatic.com/files/brand/103805.png"
        },
        {
            "id": "103804",
            "name": "金旅",
            "icon": "https://image.guazistatic.com/files/brand/103804.png"
        },
        {
            "id": "103824",
            "name": "江铃集团轻汽",
            "icon": "https://image.guazistatic.com/files/brand/103824.png"
        },
        {
            "id": "103851",
            "name": "君马汽车",
            "icon": "https://image.guazistatic.com/files/brand/103851.png"
        },
        {
            "id": "2265",
            "name": "九龙",
            "icon": "https://image.guazistatic.com/files/brand/2265.png"
        },
        {
            "id": "103781",
            "name": "江南",
            "icon": "https://image.guazistatic.com/files/brand/103781.png"
        },
        {
            "id": "102711",
            "name": "解放",
            "icon": "https://image.guazistatic.com/files/brand/102711.png"
        },
        {
            "id": "1263",
            "name": "金程",
            "icon": "https://image.guazistatic.com/files/brand/1263.png"
        }
    ],
    "K": [{
            "id": "1268",
            "name": "凯迪拉克",
            "icon": "https://image.guazistatic.com/files/brand/1268.png"
        },
        {
            "id": "2258",
            "name": "开瑞",
            "icon": "https://image.guazistatic.com/files/brand/2258.png"
        },
        {
            "id": "103775",
            "name": "凯翼",
            "icon": "https://image.guazistatic.com/files/brand/103775.png"
        },
        {
            "id": "1269",
            "name": "克莱斯勒",
            "icon": "https://image.guazistatic.com/files/brand/1269.png"
        },
        {
            "id": "103827",
            "name": "康迪",
            "icon": "https://image.guazistatic.com/files/brand/103827.png"
        },
        {
            "id": "102705",
            "name": "卡威",
            "icon": "https://image.guazistatic.com/files/brand/102705.png"
        },
        {
            "id": "103830",
            "name": "卡升",
            "icon": "https://image.guazistatic.com/files/brand/103830.png"
        },
        {
            "id": "103809",
            "name": "凯马",
            "icon": "https://image.guazistatic.com/files/brand/103809.png"
        },
        {
            "id": "102706",
            "name": "卡尔森",
            "icon": "https://image.guazistatic.com/files/brand/102706.png"
        },
        {
            "id": "102464",
            "name": "科尼赛克",
            "icon": "https://image.guazistatic.com/files/brand/102464.png"
        }
    ],
    "L": [{
            "id": "1276",
            "name": "路虎",
            "icon": "https://image.guazistatic.com/files/brand/1276.png"
        },
        {
            "id": "1209",
            "name": "铃木",
            "icon": "https://image.guazistatic.com/files/brand/1209.png"
        },
        {
            "id": "1273",
            "name": "陆风",
            "icon": "https://image.guazistatic.com/files/brand/1273.png"
        },
        {
            "id": "1270",
            "name": "猎豹",
            "icon": "https://image.guazistatic.com/files/brand/1270.png"
        },
        {
            "id": "1278",
            "name": "雷克萨斯",
            "icon": "https://image.guazistatic.com/files/brand/1278.png"
        },
        {
            "id": "1279",
            "name": "雷诺",
            "icon": "https://image.guazistatic.com/files/brand/1279.png"
        },
        {
            "id": "1274",
            "name": "力帆",
            "icon": "https://image.guazistatic.com/files/brand/1274.png"
        },
        {
            "id": "1277",
            "name": "林肯",
            "icon": "https://image.guazistatic.com/files/brand/1277.png"
        },
        {
            "id": "103849",
            "name": "领克",
            "icon": "https://image.guazistatic.com/files/brand/103849.png"
        },
        {
            "id": "2269",
            "name": "理念",
            "icon": "https://image.guazistatic.com/files/brand/2269.png"
        },
        {
            "id": "103845",
            "name": "拉达汽车",
            "icon": "https://image.guazistatic.com/files/brand/103845.png"
        },
        {
            "id": "1271",
            "name": "兰博基尼",
            "icon": "https://image.guazistatic.com/files/brand/1271.png"
        },
        {
            "id": "1281",
            "name": "劳斯莱斯",
            "icon": "https://image.guazistatic.com/files/brand/1281.png"
        },
        {
            "id": "103834",
            "name": "Lorinser",
            "icon": "https://image.guazistatic.com/files/brand/103834.png"
        },
        {
            "id": "102469",
            "name": "路特斯",
            "icon": "https://image.guazistatic.com/files/brand/102469.png"
        },
        {
            "id": "103776",
            "name": "劳伦士",
            "icon": "https://image.guazistatic.com/files/brand/103776.png"
        },
        {
            "id": "1272",
            "name": "罗孚",
            "icon": "https://image.guazistatic.com/files/brand/1272.png"
        }
    ],
    "M": [{
            "id": "1211",
            "name": "马自达",
            "icon": "https://image.guazistatic.com/files/brand/1211.png"
        },
        {
            "id": "103788",
            "name": "MG",
            "icon": "https://image.guazistatic.com/files/brand/103788.png"
        },
        {
            "id": "1284",
            "name": "MINI",
            "icon": "https://image.guazistatic.com/files/brand/1284.png"
        },
        {
            "id": "1285",
            "name": "玛莎拉蒂",
            "icon": "https://image.guazistatic.com/files/brand/1285.png"
        },
        {
            "id": "1286",
            "name": "美亚",
            "icon": "https://image.guazistatic.com/files/brand/1286.png"
        },
        {
            "id": "102716",
            "name": "迈凯伦",
            "icon": "https://image.guazistatic.com/files/brand/102716.png"
        },
        {
            "id": "103818",
            "name": "摩根",
            "icon": "https://image.guazistatic.com/files/brand/103818.png"
        },
        {
            "id": "1282",
            "name": "迈巴赫",
            "icon": "https://image.guazistatic.com/files/brand/1282.png"
        }
    ],
    "N": [{
            "id": "2271",
            "name": "纳智捷",
            "icon": "https://image.guazistatic.com/files/brand/2271.png"
        },
        {
            "id": "103814",
            "name": "南骏",
            "icon": "https://image.guazistatic.com/files/brand/103814.png"
        },
        {
            "id": "103806",
            "name": "南京金龙",
            "icon": "https://image.guazistatic.com/files/brand/103806.png"
        }
    ],
    "O": [{
            "id": "1289",
            "name": "讴歌",
            "icon": "https://image.guazistatic.com/files/brand/1289.png"
        },
        {
            "id": "1288",
            "name": "欧宝",
            "icon": "https://image.guazistatic.com/files/brand/1288.png"
        },
        {
            "id": "102481",
            "name": "欧朗",
            "icon": "https://image.guazistatic.com/files/brand/102481.png"
        }
    ],
    "Q": [{
            "id": "1292",
            "name": "起亚",
            "icon": "https://image.guazistatic.com/files/brand/1292.png"
        },
        {
            "id": "1201",
            "name": "奇瑞",
            "icon": "https://image.guazistatic.com/files/brand/1201.png"
        },
        {
            "id": "102478",
            "name": "启辰",
            "icon": "https://image.guazistatic.com/files/brand/102478.png"
        },
        {
            "id": "1275",
            "name": "青年莲花",
            "icon": "https://image.guazistatic.com/files/brand/1275.png"
        },
        {
            "id": "1291",
            "name": "庆铃",
            "icon": "https://image.guazistatic.com/files/brand/1291.png"
        },
        {
            "id": "103821",
            "name": "前途",
            "icon": "https://image.guazistatic.com/files/brand/103821.png"
        },
        {
            "id": "103846",
            "name": "乔治·巴顿",
            "icon": "https://image.guazistatic.com/files/brand/103846.png"
        }
    ],
    "R": [{
            "id": "1202",
            "name": "日产",
            "icon": "https://image.guazistatic.com/files/brand/1202.png"
        },
        {
            "id": "1293",
            "name": "荣威",
            "icon": "https://image.guazistatic.com/files/brand/1293.png"
        },
        {
            "id": "2260",
            "name": "瑞麒",
            "icon": "https://image.guazistatic.com/files/brand/2260.png"
        },
        {
            "id": "103838",
            "name": "瑞驰新能源",
            "icon": "https://image.guazistatic.com/files/brand/103838.png"
        }
    ],
    "S": [{
            "id": "1297",
            "name": "斯柯达",
            "icon": "https://image.guazistatic.com/files/brand/1297.png"
        },
        {
            "id": "1204",
            "name": "三菱",
            "icon": "https://image.guazistatic.com/files/brand/1204.png"
        },
        {
            "id": "1294",
            "name": "斯巴鲁",
            "icon": "https://image.guazistatic.com/files/brand/1294.png"
        },
        {
            "id": "102476",
            "name": "Smart",
            "icon": "https://image.guazistatic.com/files/brand/102476.png"
        },
        {
            "id": "2273",
            "name": "上汽大通",
            "icon": "https://image.guazistatic.com/files/brand/2273.png"
        },
        {
            "id": "103802",
            "name": "斯威",
            "icon": "https://image.guazistatic.com/files/brand/103802.png"
        },
        {
            "id": "1299",
            "name": "双龙",
            "icon": "https://image.guazistatic.com/files/brand/1299.png"
        },
        {
            "id": "102474",
            "name": "思铭",
            "icon": "https://image.guazistatic.com/files/brand/102474.png"
        },
        {
            "id": "1214",
            "name": "萨博",
            "icon": "https://image.guazistatic.com/files/brand/1214.png"
        },
        {
            "id": "1296",
            "name": "双环",
            "icon": "https://image.guazistatic.com/files/brand/1296.png"
        },
        {
            "id": "102700",
            "name": "陕汽通家",
            "icon": "https://image.guazistatic.com/files/brand/102700.png"
        },
        {
            "id": "103835",
            "name": "斯达泰克",
            "icon": "https://image.guazistatic.com/files/brand/103835.png"
        },
        {
            "id": "103801",
            "name": "赛麟",
            "icon": "https://image.guazistatic.com/files/brand/103801.png"
        },
        {
            "id": "103786",
            "name": "赛宝",
            "icon": "https://image.guazistatic.com/files/brand/103786.png"
        },
        {
            "id": "103766",
            "name": "Scion",
            "icon": "https://image.guazistatic.com/files/brand/103766.png"
        },
        {
            "id": "103767",
            "name": "SPRINGO",
            "icon": "https://image.guazistatic.com/files/brand/103767.png"
        },
        {
            "id": "2253",
            "name": "世爵",
            "icon": "https://image.guazistatic.com/files/brand/2253.png"
        },
        {
            "id": "103810",
            "name": "时代",
            "icon": "https://image.guazistatic.com/files/brand/103810.png"
        }
    ],
    "T": [{
            "id": "102715",
            "name": "特斯拉",
            "icon": "https://image.guazistatic.com/files/brand/102715.png"
        },
        {
            "id": "2257",
            "name": "通用",
            "icon": "https://image.guazistatic.com/files/brand/2257.png"
        },
        {
            "id": "1300",
            "name": "天马",
            "icon": "https://image.guazistatic.com/files/brand/1300.png"
        },
        {
            "id": "103836",
            "name": "泰卡特",
            "icon": "https://image.guazistatic.com/files/brand/103836.png"
        },
        {
            "id": "102717",
            "name": "腾势",
            "icon": "https://image.guazistatic.com/files/brand/102717.png"
        },
        {
            "id": "103816",
            "name": "唐骏汽车",
            "icon": "https://image.guazistatic.com/files/brand/103816.png"
        },
        {
            "id": "1301",
            "name": "通田",
            "icon": "https://image.guazistatic.com/files/brand/1301.png"
        }
    ],
    "W": [{
            "id": "1305",
            "name": "五菱",
            "icon": "https://image.guazistatic.com/files/brand/1305.png"
        },
        {
            "id": "1203",
            "name": "沃尔沃",
            "icon": "https://image.guazistatic.com/files/brand/1203.png"
        },
        {
            "id": "103829",
            "name": "WEY",
            "icon": "https://image.guazistatic.com/files/brand/103829.png"
        },
        {
            "id": "1304",
            "name": "五十铃",
            "icon": "https://image.guazistatic.com/files/brand/1304.png"
        },
        {
            "id": "2264",
            "name": "威麟",
            "icon": "https://image.guazistatic.com/files/brand/2264.png"
        },
        {
            "id": "103822",
            "name": "蔚来",
            "icon": "https://image.guazistatic.com/files/brand/103822.png"
        },
        {
            "id": "103854",
            "name": "威马汽车",
            "icon": "https://image.guazistatic.com/files/brand/103854.png"
        },
        {
            "id": "103768",
            "name": "万丰",
            "icon": "https://image.guazistatic.com/files/brand/103768.png"
        },
        {
            "id": "102714",
            "name": "威兹曼",
            "icon": "https://image.guazistatic.com/files/brand/102714.png"
        }
    ],
    "X": [{
            "id": "1208",
            "name": "现代",
            "icon": "https://image.guazistatic.com/files/brand/1208.png"
        },
        {
            "id": "1307",
            "name": "雪佛兰",
            "icon": "https://image.guazistatic.com/files/brand/1307.png"
        },
        {
            "id": "1213",
            "name": "雪铁龙",
            "icon": "https://image.guazistatic.com/files/brand/1213.png"
        },
        {
            "id": "102465",
            "name": "夏利",
            "icon": "https://image.guazistatic.com/files/brand/102465.png"
        },
        {
            "id": "1308",
            "name": "新凯",
            "icon": "https://image.guazistatic.com/files/brand/1308.png"
        },
        {
            "id": "2255",
            "name": "西雅特",
            "icon": "https://image.guazistatic.com/files/brand/2255.png"
        },
        {
            "id": "1309",
            "name": "新雅途",
            "icon": "https://image.guazistatic.com/files/brand/1309.png"
        },
        {
            "id": "103785",
            "name": "西安奥拓",
            "icon": "https://image.guazistatic.com/files/brand/103785.png"
        }
    ],
    "Y": [{
            "id": "1310",
            "name": "英菲尼迪",
            "icon": "https://image.guazistatic.com/files/brand/1310.png"
        },
        {
            "id": "1210",
            "name": "一汽",
            "icon": "https://image.guazistatic.com/files/brand/1210.png"
        },
        {
            "id": "103784",
            "name": "英致",
            "icon": "https://image.guazistatic.com/files/brand/103784.png"
        },
        {
            "id": "1311",
            "name": "依维柯",
            "icon": "https://image.guazistatic.com/files/brand/1311.png"
        },
        {
            "id": "103843",
            "name": "云度",
            "icon": "https://image.guazistatic.com/files/brand/103843.png"
        },
        {
            "id": "2261",
            "name": "永源",
            "icon": "https://image.guazistatic.com/files/brand/2261.png"
        },
        {
            "id": "103831",
            "name": "御捷",
            "icon": "https://image.guazistatic.com/files/brand/103831.png"
        },
        {
            "id": "103828",
            "name": "烟台舒驰",
            "icon": "https://image.guazistatic.com/files/brand/103828.png"
        },
        {
            "id": "1313",
            "name": "扬子",
            "icon": "https://image.guazistatic.com/files/brand/1313.png"
        },
        {
            "id": "103844",
            "name": "裕路",
            "icon": "https://image.guazistatic.com/files/brand/103844.png"
        },
        {
            "id": "1244",
            "name": "云雀",
            "icon": "https://image.guazistatic.com/files/brand/1244.png"
        },
        {
            "id": "103839",
            "name": "宇通客车",
            "icon": "https://image.guazistatic.com/files/brand/103839.png"
        }
    ],
    "Z": [{
            "id": "1318",
            "name": "众泰",
            "icon": "https://image.guazistatic.com/files/brand/1318.png"
        },
        {
            "id": "1315",
            "name": "中华",
            "icon": "https://image.guazistatic.com/files/brand/1315.png"
        },
        {
            "id": "1319",
            "name": "中兴",
            "icon": "https://image.guazistatic.com/files/brand/1319.png"
        },
        {
            "id": "103796",
            "name": "知豆",
            "icon": "https://image.guazistatic.com/files/brand/103796.png"
        },
        {
            "id": "103770",
            "name": "中欧",
            "icon": "https://image.guazistatic.com/files/brand/103770.png"
        },
        {
            "id": "103820",
            "name": "之诺",
            "icon": "https://image.guazistatic.com/files/brand/103820.png"
        },
        {
            "id": "103771",
            "name": "中顺",
            "icon": "https://image.guazistatic.com/files/brand/103771.png"
        }
    ]
}